radiocells/__init__.py
radiocells-0.3.0.dist-info/DESCRIPTION.rst
radiocells-0.3.0.dist-info/METADATA
radiocells-0.3.0.dist-info/RECORD
radiocells-0.3.0.dist-info/WHEEL
radiocells-0.3.0.dist-info/metadata.json
radiocells-0.3.0.dist-info/top_level.txt
