Metadata-Version: 2.0
Name: radiocells
Version: 0.3.0
Summary: Get position based on wifi APs in proximity and radiocells.org database.
Home-page: https://github.com/ways/locate-radiocells
Author: Lars Falk-Petersen
Author-email: dev@falkp.no
License: AGPLv3+
Keywords: location
Platform: UNKNOWN
Classifier: Development Status :: 4 - Beta
Classifier: Intended Audience :: Developers
Classifier: License :: OSI Approved :: GNU Affero General Public License v3 or later (AGPLv3+)
Classifier: Programming Language :: Python :: 2
Classifier: Programming Language :: Python :: 2.7
Classifier: Programming Language :: Python :: 3
Classifier: Programming Language :: Python :: 3.3
Classifier: Programming Language :: Python :: 3.4
Classifier: Programming Language :: Python :: 3.5
Classifier: Topic :: System :: Networking
Classifier: Operating System :: POSIX :: Linux
Classifier: Environment :: Console
Requires-Dist: wifi
Requires-Dist: requests
Requires-Dist: setuptools
Provides-Extra: json
Requires-Dist: development; extra == 'json'
